nvcs/__init__.py
nvcs/color.py
nvcs/color_scheme.json
nvcs/structure.py
nvcs-0.0.6.dist-info/LICENSE
nvcs-0.0.6.dist-info/METADATA
nvcs-0.0.6.dist-info/WHEEL
nvcs-0.0.6.dist-info/top_level.txt
nvcs-0.0.6.dist-info/RECORD
