Metadata-Version: 2.2
Name: nvcs
Version: 0.0.6
Summary: nglview wrapper for crystal structure
Author-email: Kohei Shinohara <kshinohara0508@gmail.com>
License: MIT License
Project-URL: homepage, https://github.com/lan496/nvcs
Project-URL: repository, https://github.com/lan496/nvcs
Classifier: Development Status :: 2 - Pre-Alpha
Classifier: Intended Audience :: Science/Research
Classifier: License :: OSI Approved :: MIT License
Classifier: Operating System :: OS Independent
Classifier: Programming Language :: Python
Classifier: Programming Language :: Python :: 3.9
Classifier: Programming Language :: Python :: 3.10
Classifier: Programming Language :: Python :: 3.11
Classifier: Programming Language :: Python :: 3.12
Requires-Python: >=3.9.0
License-File: LICENSE
Requires-Dist: setuptools
Requires-Dist: setuptools_scm
Requires-Dist: wheel
Requires-Dist: typing_extensions
Requires-Dist: numpy
Requires-Dist: scipy
Requires-Dist: ase
Requires-Dist: pymatgen
Requires-Dist: ipykernel
Requires-Dist: notebook>=4.2
Requires-Dist: ipywidgets
Requires-Dist: nglview>=3.0.4
Provides-Extra: dev
Requires-Dist: pytest; extra == "dev"
Requires-Dist: pre-commit; extra == "dev"
Requires-Dist: mypy; extra == "dev"
Requires-Dist: toml; extra == "dev"
